currency_converter_wolf_skullcave/__about__.py
currency_converter_wolf_skullcave/__init__.py
currency_converter_wolf_skullcave/currency.py
currency_converter_wolf_skullcave/main.py
currency_converter_wolf_skullcave-3.0.0.dist-info/METADATA
currency_converter_wolf_skullcave-3.0.0.dist-info/WHEEL
currency_converter_wolf_skullcave-3.0.0.dist-info/entry_points.txt
currency_converter_wolf_skullcave-3.0.0.dist-info/licenses/LICENSE.txt
currency_converter_wolf_skullcave-3.0.0.dist-info/RECORD
