Metadata-Version: 2.4
Name: currency-converter-wolf-skullcave
Version: 3.0.0
Summary: Convert USD and EUR to ZAR
Project-URL: Documentation, https://github.com/wolfSkullCave/currency-converter-wolf-skullcave#readme
Project-URL: Issues, https://github.com/wolfSkullCave/currency-converter-wolf-skullcave/issues
Project-URL: Source, https://github.com/wolfSkullCave/currency-converter-wolf-skullcave
Author-email: wolf_skullcave <7805222+wolfSkullCave@users.noreply.github.com>
License-Expression: MIT
License-File: LICENSE.txt
Classifier: Development Status :: 4 - Beta
Classifier: Programming Language :: Python
Classifier: Programming Language :: Python :: 3.8
Classifier: Programming Language :: Python :: 3.9
Classifier: Programming Language :: Python :: 3.10
Classifier: Programming Language :: Python :: 3.11
Classifier: Programming Language :: Python :: 3.12
Classifier: Programming Language :: Python :: Implementation :: CPython
Classifier: Programming Language :: Python :: Implementation :: PyPy
Requires-Python: >=3.8
Requires-Dist: beautifulsoup4
Requires-Dist: typer
